{
  "type": "prediction_scoring",
  "neverRecomputeExistingPartitions": false,
  "optionalDependencies": false,
  "params": {
    "containerSelection": {
      "containerMode": "INHERIT"
    }
  },
  "customMeta": {
    "kv": {}
  },
  "redispatchPartitioning": false,
  "maxRunningActivities": 0,
  "variables": {},
  "dkuProperties": [],
  "inputs": {
    "model": {
      "items": [
        {
          "ref": "WE1mmMLD",
          "deps": []
        }
      ]
    },
    "main": {
      "items": [
        {
          "ref": "to_score",
          "deps": []
        }
      ]
    }
  },
  "outputs": {
    "main": {
      "items": [
        {
          "ref": "scored",
          "appendMode": false
        }
      ]
    }
  },
  "labels": [],
  "versionTag": {
    "versionNumber": 2,
    "lastModifiedBy": {
      "login": "amain"
    },
    "lastModifiedOn": 1656528705293
  },
  "creationTag": {
    "versionNumber": 0,
    "lastModifiedBy": {
      "login": "admin"
    },
    "lastModifiedOn": 1604117085396
  },
  "tags": [],
  "customFields": {},
  "checklists": {
    "checklists": []
  }
}